OiWiki202037Fix1/README.md
OiWiki202037Fix1/__init__.py
OiWiki202037Fix1/__main__.py
OiWiki202037Fix1/file.epub
OiWiki202037Fix1/index.html
OiWiki202037Fix1/css/__init__.py
OiWiki202037Fix1/css/annotations.css
OiWiki202037Fix1/css/main.css
OiWiki202037Fix1/css/normalize.css
OiWiki202037Fix1/css/popup.css
OiWiki202037Fix1/font/__init__.py
OiWiki202037Fix1/font/fontello.eot
OiWiki202037Fix1/font/fontello.svg
OiWiki202037Fix1/font/fontello.ttf
OiWiki202037Fix1/font/fontello.woff
OiWiki202037Fix1/img/__init__.py
OiWiki202037Fix1/img/annotator-glyph-sprite.png
OiWiki202037Fix1/img/annotator-icon-sprite.png
OiWiki202037Fix1/img/apple-touch-icon.png
OiWiki202037Fix1/img/cancelfullscreen.png
OiWiki202037Fix1/img/close.png
OiWiki202037Fix1/img/fullscreen.png
OiWiki202037Fix1/img/loader.gif
OiWiki202037Fix1/img/menu-icon.png
OiWiki202037Fix1/img/save.png
OiWiki202037Fix1/img/saved.png
OiWiki202037Fix1/img/settings-s.png
OiWiki202037Fix1/img/settings.png
OiWiki202037Fix1/img/star.png
OiWiki202037Fix1/js/__init__.py
OiWiki202037Fix1/js/epub.js
OiWiki202037Fix1/js/epub.min.js
OiWiki202037Fix1/js/epub.min.map
OiWiki202037Fix1/js/hooks.min.js
OiWiki202037Fix1/js/hooks.min.map
OiWiki202037Fix1/js/reader.js
OiWiki202037Fix1/js/reader.js.map
OiWiki202037Fix1/js/reader.min.js
OiWiki202037Fix1/js/reader.min.map
OiWiki202037Fix1/js/hooks/__init__.py
OiWiki202037Fix1/js/hooks/extensions/__init__.py
OiWiki202037Fix1/js/hooks/extensions/highlight.js
OiWiki202037Fix1/js/libs/__init__.py
OiWiki202037Fix1/js/libs/jquery.min.js
OiWiki202037Fix1/js/libs/localforage.min.js
OiWiki202037Fix1/js/libs/screenfull.js
OiWiki202037Fix1/js/libs/screenfull.min.js
OiWiki202037Fix1/js/libs/zip.min.js
OiWiki202037Fix1/js/plugins/__init__.py
OiWiki202037Fix1/js/plugins/hypothesis.js
OiWiki202037Fix1/js/plugins/search.js
oi_wiki_2020_3_7_fix1-2025.3.24.0.dist-info/METADATA
oi_wiki_2020_3_7_fix1-2025.3.24.0.dist-info/WHEEL
oi_wiki_2020_3_7_fix1-2025.3.24.0.dist-info/entry_points.txt
oi_wiki_2020_3_7_fix1-2025.3.24.0.dist-info/top_level.txt
oi_wiki_2020_3_7_fix1-2025.3.24.0.dist-info/RECORD
